rasch_pkg/__init__.py
rasch_pkg/rasch_evaluator.py
rasch_pkg/rasch_model.py
rasch_pkg-1.0.1.dist-info/licenses/LICENSE
rasch_pkg-1.0.1.dist-info/METADATA
rasch_pkg-1.0.1.dist-info/WHEEL
rasch_pkg-1.0.1.dist-info/top_level.txt
rasch_pkg-1.0.1.dist-info/RECORD
