Metadata-Version: 2.4
Name: rasch-pkg
Version: 1.0.1
Summary: Rasch modeli asosida o'quvchilarni baholash tizimi - Student assessment system based on Rasch model
Author-email: Muhammad Ali <muhammadali@example.com>
Maintainer-email: Muhammad Ali <muhammadali@example.com>
License: MIT
Project-URL: Homepage, https://github.com/muhammadali/rasch-pkg
Project-URL: Documentation, https://github.com/muhammadali/rasch-pkg#readme
Project-URL: Repository, https://github.com/muhammadali/rasch-pkg.git
Project-URL: Bug Tracker, https://github.com/muhammadali/rasch-pkg/issues
Keywords: rasch-model,student-assessment,educational-measurement,psychometrics,item-response-theory,uzbekistan,education
Classifier: Development Status :: 5 - Production/Stable
Classifier: Intended Audience :: Education
Classifier: Intended Audience :: Science/Research
Classifier: License :: OSI Approved :: MIT License
Classifier: Operating System :: OS Independent
Classifier: Programming Language :: Python :: 3
Classifier: Programming Language :: Python :: 3.8
Classifier: Programming Language :: Python :: 3.9
Classifier: Programming Language :: Python :: 3.10
Classifier: Programming Language :: Python :: 3.11
Classifier: Programming Language :: Python :: 3.12
Classifier: Topic :: Education
Classifier: Topic :: Scientific/Engineering
Classifier: Topic :: Scientific/Engineering :: Information Analysis
Classifier: Topic :: Software Development :: Libraries :: Python Modules
Requires-Python: >=3.8
License-File: LICENSE
Requires-Dist: numpy>=1.21.0
Requires-Dist: pandas>=1.3.0
Requires-Dist: openpyxl>=3.0.0
Requires-Dist: psycopg2-binary>=2.9.0
Provides-Extra: dev
Requires-Dist: pytest>=7.0.0; extra == "dev"
Requires-Dist: pytest-cov>=4.0.0; extra == "dev"
Requires-Dist: black>=22.0.0; extra == "dev"
Requires-Dist: ruff>=0.1.0; extra == "dev"
Requires-Dist: mypy>=1.0.0; extra == "dev"
Provides-Extra: docs
Requires-Dist: sphinx>=5.0.0; extra == "docs"
Requires-Dist: sphinx-rtd-theme>=1.0.0; extra == "docs"
Dynamic: license-file
